scaleogram/__init__.py
scaleogram/cws.py
scaleogram/test.py
scaleogram/unittests.py
scaleogram/wfun.py
scaleogram-0.9.5.dist-info/DESCRIPTION.rst
scaleogram-0.9.5.dist-info/METADATA
scaleogram-0.9.5.dist-info/RECORD
scaleogram-0.9.5.dist-info/WHEEL
scaleogram-0.9.5.dist-info/metadata.json
scaleogram-0.9.5.dist-info/top_level.txt
