Metadata-Version: 1.1
Name: scaleogram
Version: 0.9.5
Summary: User friendly scaleogram plot for Continuous Wavelet Transform
Home-page: https://github.com/alsauve/scaleogram
Author: Alexandre Sauve
Author-email: asauve@gmail.com
License: UNKNOWN
Platform: UNKNOWN
Classifier: Programming Language :: Python :: 3
Classifier: License :: OSI Approved :: MIT License
Classifier: Operating System :: OS Independent
Classifier: Topic :: Scientific/Engineering :: Information Analysis
Classifier: Topic :: Scientific/Engineering :: Visualization
Classifier: Intended Audience :: Information Technology
Classifier: Intended Audience :: Science/Research
